
[
    {
        "path": "von.jpg",
        "caption": "Von Isaac R. Baban"
    },
    {
        "path": "vista.jpg",
        "caption": "Jonathan P. Vista"
    },
    {
        "path": "mercado.jpg",
        "caption": "Aaron Mercado"
    },
    {
        "path": "soralbo.jpg",
        "caption": "Roger Joshua T. Soralbo"
    },
    {
        "path": "dave.jpg",
        "caption":"Christian Dave O. Morales"
    },
    {
        "path": "rexie.jpg",
        "caption": "Rexie Alfaro"
    },
    {
        "path": "aeron-carillia.jpg",
        "caption": "John Carilla"
    },
    {
        "path":"ruzzel.jpg",
        "caption": "John Ruzell M. Rivera"
    }
  
   
]